<HBProfile>
	<Name>Cauldron of Flames [WG] ($Rev$)</Name>
	
	<MinLevel>77</MinLevel>  // minimum level
	<MaxLevel>81</MaxLevel> // change to 86 if you're doing this at level 85
	
	<MinDurability>0.3</MinDurability>
	<MinFreeBagSlots>1</MinFreeBagSlots> // How many free bag slots to keep until you need to sell / mail
	
	<Factions>91</Factions> // This is considered a "[Elemental]"
   
	<Hotspots> // This are the points around the area you want to farm
		<Hotspot X="4187.499" Y="1841.418" Z="359.4431" />
		<Hotspot X="4237.971" Y="1893.964" Z="355.2934" />
		<Hotspot X="4325.182" Y="1924.744" Z="356.067" />
		<Hotspot X="4279.227" Y="1862.023" Z="353.2209" />
		<Hotspot X="4331.919" Y="1829.466" Z="355.6594" />
		<Hotspot X="4252.032" Y="1798.209" Z="351.2871" />
		<Hotspot X="4288.42" Y="1754.458" Z="350.4885" />
		<Hotspot X="4362.734" Y="1775.917" Z="353.8306" />
		<Hotspot X="4407.264" Y="1824.904" Z="359.9005" />
		<Hotspot X="4467.622" Y="1857.903" Z="378.1476" />
		<Hotspot X="4454.512" Y="1800.456" Z="379.4637" />
		<Hotspot X="4448.133" Y="1730.929" Z="379.4464" />
		<Hotspot X="4387.168" Y="1752.877" Z="363.4456" />
	</Hotspots>
</HBProfile>