<HBProfile>
  <Name>Tony's Badlands 175-230 ($Rev$)</Name>
  <MinDurability>0.4</MinDurability>
  <MinFreeBagSlots>1</MinFreeBagSlots>
  
  <MinLevel>1</MinLevel>
  <MaxLevel>86</MaxLevel>
  <Factions>99999</Factions>
  
  <MailGrey>False</MailGrey>
  <MailWhite>True</MailWhite>
  <MailGreen>True</MailGreen>
  <MailBlue>True</MailBlue>
  <MailPurple>True</MailPurple>
 
  <SellGrey>True</SellGrey>
  <SellWhite>True</SellWhite>
  <SellGreen>False</SellGreen>
  <SellBlue>False</SellBlue>
  <SellPurple>False</SellPurple>

	<Vendors>

	</Vendors>
	
	<Mailboxes>

	</Mailboxes>

  <Hotspots>
    <Hotspot X="-7103.16" Y="-2860.316" Z="348.0222" />
    <Hotspot X="-7114.827" Y="-3007.687" Z="295.3862" />
    <Hotspot X="-7122.517" Y="-3207.974" Z="292.1343" />
    <Hotspot X="-7115.973" Y="-3406.781" Z="283.2773" />
    <Hotspot X="-7091" Y="-3518.48" Z="283.9939" />
    <Hotspot X="-6971.534" Y="-3636.79" Z="280.9631" />
    <Hotspot X="-6777.906" Y="-3610.893" Z="276.5334" />
    <Hotspot X="-6770.325" Y="-3797.005" Z="287.0834" />
    <Hotspot X="-6923.817" Y="-3913.17" Z="303.9725" />
    <Hotspot X="-6863.845" Y="-4071.761" Z="299.4122" />
    <Hotspot X="-6685.803" Y="-4103.757" Z="333.484" />
    <Hotspot X="-6490.169" Y="-4125.316" Z="306.775" />
    <Hotspot X="-6438.09" Y="-4010.501" Z="306.7165" />
    <Hotspot X="-6426.896" Y="-3816.801" Z="330.6399" />
    <Hotspot X="-6350.748" Y="-3632.272" Z="304.1985" />
    <Hotspot X="-6290.919" Y="-3506.842" Z="293.4471" />
    <Hotspot X="-6214.521" Y="-3408.794" Z="292.8218" />
    <Hotspot X="-6390.382" Y="-3324.347" Z="293.0721" />
    <Hotspot X="-6512.343" Y="-3187.082" Z="334.2424" />
    <Hotspot X="-6564.786" Y="-3013.213" Z="306.062" />
    <Hotspot X="-6647.008" Y="-2830.575" Z="287.657" />
    <Hotspot X="-6645.647" Y="-2631.628" Z="286.8184" />
    <Hotspot X="-6607.295" Y="-2436.578" Z="299.1327" />
    <Hotspot X="-6610.606" Y="-2280.108" Z="304.7511" />
    <Hotspot X="-6768.198" Y="-2201.451" Z="325.5428" />
    <Hotspot X="-6920.249" Y="-2325.043" Z="293.1454" />
    <Hotspot X="-7105.612" Y="-2388.28" Z="292.4668" />
    <Hotspot X="-7184.458" Y="-2554.829" Z="296.193" />
    <Hotspot X="-7139.134" Y="-2694.859" Z="283.4662" />
    <Hotspot X="-7128.322" Y="-2833.291" Z="301.1225" />
  </Hotspots>
  <Blackspots>
  </Blackspots>
</HBProfile>
