<HBProfile>
  <Name>_-*GB2*-_ AIO Zul'Drak by Bengan12 v1.0 ($Rev$)</Name>
  <MinDurability>0.3</MinDurability>
  <MinFreeBagSlots>3</MinFreeBagSlots>
  
  <MinLevel>1</MinLevel>
  <MaxLevel>86</MaxLevel>
  <Factions>99999</Factions>
  
  <MailGrey>False</MailGrey>
  <MailWhite>True</MailWhite>
  <MailGreen>True</MailGreen>
  <MailBlue>True</MailBlue>
  <MailPurple>True</MailPurple>
 
  <SellGrey>True</SellGrey>
  <SellWhite>True</SellWhite>
  <SellGreen>False</SellGreen>
  <SellBlue>False</SellBlue>
  <SellPurple>False</SellPurple>

  <Vendors>
    <Vendor Name="Arlen Brighthammer" Entry="28796" Type="Repair" X="5409.375" Y="-2656.25" Z="303.9539" />
  </Vendors>
  
  <Mailboxes>
    <Mailbox X="5486.991" Y="-2642.352" Z="306.7451" />
    <Mailbox X="5461.4" Y="-2595.558" Z="305.6241" />
    <Mailbox X="5412.445" Y="-2621.183" Z="306.1304" />
  </Mailboxes>

  <Blackspots>

  </Blackspots>

  <Hotspots>
    <Hotspot X="6608.794" Y="-3279.077" Z="508.7359" />
    <Hotspot X="6541.125" Y="-3341.422" Z="494.5437" />
    <Hotspot X="6480.178" Y="-3415.464" Z="480.8623" />
    <Hotspot X="6376.614" Y="-3298.028" Z="454.5578" />
    <Hotspot X="6185.317" Y="-3307.947" Z="467.2209" />
    <Hotspot X="6068.202" Y="-3315.838" Z="473.4654" />
    <Hotspot X="5935.833" Y="-3290.088" Z="477.7641" />
    <Hotspot X="5754.493" Y="-3233.361" Z="452.2256" />
    <Hotspot X="5522.956" Y="-3036.885" Z="413.4568" />
    <Hotspot X="5647.015" Y="-3389.224" Z="431.4211" />
    <Hotspot X="5707.284" Y="-3515.753" Z="549.4343" />
    <Hotspot X="5753.277" Y="-3584.099" Z="559.8775" />
    <Hotspot X="5828.442" Y="-3595.012" Z="550.533" />
    <Hotspot X="5832.54" Y="-3792.46" Z="484.7742" />
    <Hotspot X="5955.624" Y="-4039.468" Z="477.1129" />
    <Hotspot X="6051.37" Y="-4238.811" Z="366.884" />
    <Hotspot X="6133.374" Y="-4191.194" Z="468.7943" />
    <Hotspot X="6298.417" Y="-4160.57" Z="492.7332" />
    <Hotspot X="6418.43" Y="-4131.343" Z="504.1926" />
    <Hotspot X="6501.778" Y="-4179.436" Z="487.2005" />
    <Hotspot X="6525.848" Y="-4174.916" Z="492.1689" />
    <Hotspot X="6568.1" Y="-4139.998" Z="505.9605" />
    <Hotspot X="6674.011" Y="-4144.461" Z="521.4465" />
    <Hotspot X="6860.919" Y="-4143.238" Z="523.7263" />
    <Hotspot X="6794.434" Y="-4295.629" Z="501.2697" />
    <Hotspot X="6836.539" Y="-4563.985" Z="507.4486" />
    <Hotspot X="6528.438" Y="-4521.664" Z="565.4893" />
    <Hotspot X="6229.453" Y="-4483.015" Z="533.4268" />
    <Hotspot X="6144.629" Y="-4423.608" Z="528.1841" />
    <Hotspot X="6127.058" Y="-4409.975" Z="522.827" />
    <Hotspot X="6010.383" Y="-4333.591" Z="411.2019" />
    <Hotspot X="5732.792" Y="-4371.234" Z="432.2549" />
    <Hotspot X="5664.378" Y="-4376.067" Z="435.4892" />
    <Hotspot X="5426.193" Y="-4451.353" Z="432.8117" />
    <Hotspot X="5273.665" Y="-4482.215" Z="436.3367" />
    <Hotspot X="5179.574" Y="-4304.647" Z="406.3898" />
    <Hotspot X="5232.688" Y="-4184.557" Z="401.1902" />
    <Hotspot X="5316.751" Y="-3874.216" Z="425.8129" />
    <Hotspot X="5304.939" Y="-3825.819" Z="429.8654" />
    <Hotspot X="5206.813" Y="-3706.304" Z="422.2585" />
    <Hotspot X="5214.878" Y="-3590.252" Z="448.8431" />
    <Hotspot X="5215.184" Y="-3451.583" Z="356.313" />
    <Hotspot X="5045.008" Y="-3478.627" Z="343.8435" />
    <Hotspot X="4945.376" Y="-3556.478" Z="349.5157" />
    <Hotspot X="4901.916" Y="-3573.65" Z="350.8238" />
    <Hotspot X="4871.543" Y="-3538.556" Z="356.9467" />
    <Hotspot X="4944.189" Y="-3271.171" Z="350.3474" />
    <Hotspot X="5200.112" Y="-3293.523" Z="378.1866" />
    <Hotspot X="5334.157" Y="-3189.011" Z="392.8523" />
    <Hotspot X="5077.264" Y="-3025.995" Z="395.4008" />
    <Hotspot X="4951.05" Y="-2875.661" Z="376.4664" />
    <Hotspot X="4859.746" Y="-2805.027" Z="368.2183" />
    <Hotspot X="5124.795" Y="-2791.166" Z="401.8666" />
    <Hotspot X="5203.434" Y="-2749.496" Z="409.8524" />
    <Hotspot X="5375.249" Y="-2559.441" Z="404.7038" />
    <Hotspot X="5577.759" Y="-2775.585" Z="349.1989" />
    <Hotspot X="5653.138" Y="-2488.586" Z="344.8546" />
    <Hotspot X="5553" Y="-2474.875" Z="344.8869" />
    <Hotspot X="5494.508" Y="-2341.487" Z="357.6685" />
    <Hotspot X="5498.198" Y="-2091.316" Z="382.9461" />
    <Hotspot X="5334.282" Y="-2087.296" Z="377.4385" />
    <Hotspot X="5146.444" Y="-2166.529" Z="356.5061" />
    <Hotspot X="5278.254" Y="-2395.249" Z="366.9579" />
    <Hotspot X="5168.881" Y="-2486.024" Z="343.6195" />
    <Hotspot X="5004.951" Y="-2493.92" Z="378.1624" />
    <Hotspot X="4776.222" Y="-2534.728" Z="291.4808" />
    <Hotspot X="4743.863" Y="-2355.371" Z="275.2981" />
    <Hotspot X="4788.949" Y="-2229.202" Z="271.3644" />
    <Hotspot X="4921.107" Y="-2110.116" Z="278.1134" />
    <Hotspot X="5026.132" Y="-2051.21" Z="285.666" />
    <Hotspot X="5130.805" Y="-1942.176" Z="332.5242" />
    <Hotspot X="5155.3" Y="-1916.589" Z="319.9461" />
    <Hotspot X="5143.709" Y="-1874.619" Z="301.3713" />
    <Hotspot X="4993.612" Y="-1796.852" Z="283.6653" />
    <Hotspot X="4864.815" Y="-1798.698" Z="281.6942" />
    <Hotspot X="4837.918" Y="-1669.396" Z="279.0134" />
    <Hotspot X="4977.219" Y="-1649.162" Z="283.7946" />
    <Hotspot X="5119.406" Y="-1636.29" Z="278.8292" />
    <Hotspot X="5124.665" Y="-1400.595" Z="285.8517" />
    <Hotspot X="5118.764" Y="-1188.415" Z="295.9297" />
    <Hotspot X="5443.952" Y="-1301.113" Z="308.7662" />
    <Hotspot X="5419.027" Y="-1511.516" Z="312.5839" />
    <Hotspot X="5348.765" Y="-1646.03" Z="278.9401" />
    <Hotspot X="5377.862" Y="-1731.637" Z="266.052" />
    <Hotspot X="5355.773" Y="-1816.768" Z="261.0702" />
    <Hotspot X="5423.992" Y="-1868.152" Z="266.6788" />
    <Hotspot X="5537.097" Y="-1754.098" Z="265.1247" />
    <Hotspot X="5678.03" Y="-1635.614" Z="267.9659" />
    <Hotspot X="5796.514" Y="-1474.227" Z="269.5003" />
    <Hotspot X="6054.584" Y="-1730.292" Z="273.2273" />
    <Hotspot X="5920.038" Y="-1845.759" Z="289.2202" />
    <Hotspot X="5818.77" Y="-2138.025" Z="296.3381" />
    <Hotspot X="5732.12" Y="-2364.784" Z="371.8759" />
    <Hotspot X="5977.047" Y="-2365.183" Z="418.9641" />
    <Hotspot X="6159.484" Y="-2306.966" Z="412.6024" />
    <Hotspot X="6288.916" Y="-2163.007" Z="337.1455" />
    <Hotspot X="6293.656" Y="-2247.228" Z="354.4243" />
    <Hotspot X="6293.623" Y="-2268.671" Z="389.1773" />
    <Hotspot X="6283.254" Y="-2446.625" Z="383.6812" />
    <Hotspot X="6254.479" Y="-2659.255" Z="358.1301" />
    <Hotspot X="6159.289" Y="-2651.209" Z="363.3553" />
    <Hotspot X="6088.187" Y="-2699.923" Z="366.6473" />
    <Hotspot X="5807.853" Y="-2741.039" Z="385.413" />
    <Hotspot X="5988.391" Y="-2814.096" Z="384.4529" />
    <Hotspot X="6291.953" Y="-2915.53" Z="440.5946" />
    <Hotspot X="6474.769" Y="-3172.857" Z="478.0734" />
    <Hotspot X="6594.138" Y="-3165.14" Z="496.6003" />
  </Hotspots>
</HBProfile>
