<HBProfile>
	<Name>River Delta - Uldum ($Rev$)</Name>
	<MinLevel>1</MinLevel>
	<MaxLevel>86</MaxLevel>
	<MinDurability>0.3</MinDurability>
	<MinFreeBagSlots>3</MinFreeBagSlots>
	<SellGrey>True</SellGrey>
	<!-- <GrindArea>
	
	<FishingPools Entry="" Name="" />
	 -->
    <Hotspots>
<!-- start of West side -->
<!-- -->
<Hotspot X="-10658.18" Y="1521.643" Z="43.38686" /> 
<Hotspot X="-10703.74" Y="1450.344" Z="28.91709" />
<Hotspot X="-10743.3" Y="1399.635" Z="36.24039" />
<Hotspot X="-10770.43" Y="1310.634" Z="31.17159" />
<Hotspot X="-10757.3" Y="1214.34" Z="26.07908" />
<Hotspot X="-10748.3" Y="1122.016" Z="21.285" />
<Hotspot X="-10726.84" Y="1003.295" Z="21.1032" />
<Hotspot X="-10760.12" Y="963.4223" Z="15.31273" />
<Hotspot X="-10783.91" Y="917.5269" Z="16.50125" />
<Hotspot X="-10771.82" Y="821.0034" Z="14.29053" />
<Hotspot X="-10805.92" Y="750.3822" Z="19.08794" />
<Hotspot X="-10853.52" Y="658.5181" Z="13.4591" />
<Hotspot X="-10909.58" Y="589.6854" Z="22.0635" />
<Hotspot X="-10948.46" Y="511.4032" Z="21.22446" />
<Hotspot X="-10957.46" Y="434.9951" Z="20.47198" />
<Hotspot X="-10979.25" Y="319.8457" Z="29.71671" />
<Hotspot X="-11024.21" Y="228.9835" Z="22.12392" />
<Hotspot X="-11064.87" Y="159.3191" Z="20.35621" />
<Hotspot X="-11079.53" Y="92.81532" Z="22.92186" />
<Hotspot X="-11097.83" Y="-0.7856445" Z="26.50239" />
<Hotspot X="-11098.17" Y="-76.61371" Z="29.39735" />
<Hotspot X="-11113.86" Y="-133.7584" Z="21.24558" />
<Hotspot X="-11189.78" Y="-157.5833" Z="18.5213" />
<Hotspot X="-11261.35" Y="-172.4131" Z="19.35053" />
<Hotspot X="-11325.81" Y="-216.3813" Z="20.25008" />
<Hotspot X="-11467.27" Y="-301.2165" Z="22.14664" />
<Hotspot X="-11617.37" Y="-382.7858" Z="24.10989" />
<Hotspot X="-11743.54" Y="-436.0437" Z="25.68296" />
<Hotspot X="-11774.33" Y="-488.2057" Z="26.3927" />
<Hotspot X="-11762.04" Y="-544.8691" Z="27.08886" />
<Hotspot X="-11730.32" Y="-657.1815" Z="22.17556" />
<Hotspot X="-11691.61" Y="-785.1464" Z="11.09899" />
<Hotspot X="-11645.92" Y="-954.7353" Z="10.14836" />
<Hotspot X="-11624.71" Y="-1043.921" Z="11.18943" />
<Hotspot X="-11580.56" Y="-1115.367" Z="12.16412" /> 
 <!-- end of west side, we're near the southwest delta -->


<Hotspot X="-11566.53" Y="-1124.806" Z="12.31315" /> <!-- Beginning of delta to east side -->
<Hotspot X="-11577.03" Y="-1170.905" Z="9.980783" />
<Hotspot X="-11593.44" Y="-1224.883" Z="7.517519" />
<Hotspot X="-11585.48" Y="-1273.244" Z="5.288631" />
<Hotspot X="-11584.52" Y="-1319.71" Z="3.245387" />
<Hotspot X="-11529.96" Y="-1353.249" Z="8.11808" />
<Hotspot X="-11459.94" Y="-1388.96" Z="6.333996" />
<Hotspot X="-11438.85" Y="-1450.802" Z="4.236027" />
<Hotspot X="-11375.81" Y="-1487.861" Z="4.478745" />
<Hotspot X="-11343.28" Y="-1526.872" Z="4.831301" />
<Hotspot X="-11322.99" Y="-1578.225" Z="5.602315" />
<Hotspot X="-11326.03" Y="-1634.139" Z="6.406384" />
<Hotspot X="-11305.46" Y="-1683.712" Z="7.206739" />
<Hotspot X="-11301.55" Y="-1745.663" Z="8.112198" />
<Hotspot X="-11292.53" Y="-1792.586" Z="8.790364" />
<Hotspot X="-11244.54" Y="-1858.544" Z="9.952085" />
<Hotspot X="-11272.41" Y="-1906.826" Z="10.91808" />
<Hotspot X="-11299.43" Y="-1972.981" Z="11.94016" />
<Hotspot X="-11252.58" Y="-2016.506" Z="12.96112" />
<Hotspot X="-11205.75" Y="-2046.048" Z="8.978201" />
<Hotspot X="-11215.55" Y="-2098.135" Z="7.91974" /> <!-- end of delta east side -->
	</Hotspots>
	<!-- </GrindArea> -->
	<Blackspots>
<Blackspot X="-11233.47" Y="-1487.058" Z="5.400975" Radius="6.170819" />

	</Blackspots>
 
  <Mailboxes>
		<Mailbox X="-8352.407" Y="784.2535" Z="151.3457" />
		<Mailbox X="-9429.111" Y="-967.3807" Z="111.0115" />
  </Mailboxes>
  <Vendors>
		<Vendor Name="&quot;Chesty&quot; Jake" Entry="49409" Type="Repair" X="-8353.455" Y="759.2292" Z="151.4582" />
		<Vendor Name="Blacksmith Abasi" Entry="48617" Type="Repair" X="-9404.68" Y="-906.438" Z="112.5407" />
  </Vendors>
  <ProtectedItems>
    <Item id="19970" name="Arcanite Fishing Pole" />
    <Item id="6367" name="Big Iron Fishing Pole" />
    <Item id="12225" name="Blump Family Fishing Pole" />
    <Item id="45991" name="Bone Fishing Pole" />
    <Item id="6366" name="Darkwood Fishing Pole" />
    <Item id="3567" name="Dwarven Fishing Pole" />
    <Item id="6256" name="Fishing Pole" />
    <Item id="4598" name="Goblin Fishing Pole" />
    <Item id="45992" name="Jeweled Fishing Pole" />
    <Item id="44050" name="Mastercraft Kalu'ak Fishing Pole" />
    <Item id="45858" name="Nat's Lucky Fishing Pole" />
    <Item id="25978" name="Seth's Graphite Fishing Pole" />
    <Item id="6365" name="Strong Fishing Pole" />
    <Item id="41810" name="Fangtooth Herring" />
    <Item id="40199" name="Pygmy Suckerfish" />
    <Item id="37705" name="Crystallized Water" />
    <Item id="44475" name="Reinforced Crate" />
    <Item id="50289" name="Blacktip Shark" />
    <Item id="44703" name="Dark Herring" />
    <Item id="44505" name="Dustbringer" />
    <Item id="46109" name="Sea Turtle" />
    <Item id="8227" name="Elixir of Water Walking" />
  </ProtectedItems>
  <ForceMail>
  </ForceMail>

  </HBProfile>